PoseAnalyzer/Pose.py
PoseAnalyzer/PoseAnalyzer.py
PoseAnalyzer/__init__.py
PoseAnalyzer/helpers/__init__.py
PoseAnalyzer/helpers/estimation/__init__.py
PoseAnalyzer/helpers/estimation/kalman.py
PoseAnalyzer/helpers/geometry/__init__.py
PoseAnalyzer/helpers/geometry/euclidian.py
PoseAnalyzer/helpers/geometry/orientation.py
PoseAnalyzer/helpers/ui/__init__.py
PoseAnalyzer/helpers/ui/opencv/__init__.py
PoseAnalyzer/helpers/ui/pillow/__init__.py
PoseAnalyzer/helpers/ui/pygame/__init__.py
PoseAnalyzer/helpers/ui/pygame/colors.py
PoseAnalyzer/helpers/ui/sqtui/__init__.py
PoseAnalyzer-0.0.2.dist-info/LICENSE
PoseAnalyzer-0.0.2.dist-info/METADATA
PoseAnalyzer-0.0.2.dist-info/WHEEL
PoseAnalyzer-0.0.2.dist-info/top_level.txt
PoseAnalyzer-0.0.2.dist-info/RECORD
