Metadata-Version: 2.1
Name: PoseAnalyzer
Version: 0.0.2
Summary: A python library for hands detection and features extraction based on mediapipe library
Home-page: https://github.com/ParisNeo/PoseAnalyzer
Author: Saifeddine ALOUI
Author-email: aloui.saifeddine@gmail.com
License: UNKNOWN
Platform: UNKNOWN
Classifier: Programming Language :: Python :: 3.8
Classifier: License :: OSI Approved :: MIT License
Classifier: Operating System :: OS Independent
Requires-Dist: numpy
Requires-Dist: mediapipe
Requires-Dist: scipy
Requires-Dist: opencv-python
Requires-Dist: Pillow
Requires-Dist: cssutils
Requires-Dist: sqtui
Provides-Extra: dev
